terminal_monkeytype/__init__.py
terminal_monkeytype/main.py
terminal_monkeytype-1.0.0.dist-info/METADATA
terminal_monkeytype-1.0.0.dist-info/WHEEL
terminal_monkeytype-1.0.0.dist-info/entry_points.txt
terminal_monkeytype-1.0.0.dist-info/top_level.txt
terminal_monkeytype-1.0.0.dist-info/RECORD
