Metadata-Version: 2.4
Name: terminal-monkeytype
Version: 1.0.0
Summary: A clean terminal typing test inspired by Monkeytype
Author: Aaquib Ali
License: MIT
Requires-Python: >=3.8
Requires-Dist: prompt_toolkit
Requires-Dist: rich
